flask_breadcrumbs/__init__.py
flask_breadcrumbs/version.py
Flask_Breadcrumbs-0.5.0.dist-info/AUTHORS.rst
Flask_Breadcrumbs-0.5.0.dist-info/LICENSE
Flask_Breadcrumbs-0.5.0.dist-info/METADATA
Flask_Breadcrumbs-0.5.0.dist-info/WHEEL
Flask_Breadcrumbs-0.5.0.dist-info/top_level.txt
Flask_Breadcrumbs-0.5.0.dist-info/RECORD
